ytscriber/__init__.py
ytscriber/batch.py
ytscriber/cli.py
ytscriber/config.py
ytscriber/csv_handler.py
ytscriber/downloader.py
ytscriber/exceptions.py
ytscriber/extractor.py
ytscriber/init.py
ytscriber/logging_config.py
ytscriber/metadata.py
ytscriber/models.py
ytscriber/paths.py
ytscriber/py.typed
ytscriber/summarizer.py
ytscriber/sync.py
ytscriber/utils.py
ytscriber-1.2.2.dist-info/licenses/LICENSE
ytscriber-1.2.2.dist-info/METADATA
ytscriber-1.2.2.dist-info/WHEEL
ytscriber-1.2.2.dist-info/entry_points.txt
ytscriber-1.2.2.dist-info/top_level.txt
ytscriber-1.2.2.dist-info/RECORD
