Metadata-Version: 2.4
Name: ytscriber
Version: 1.2.2
Summary: Download YouTube transcripts and manage channel archives
Author: Daniel Paredes
License: MIT
Project-URL: Homepage, https://github.com/dparedesi/YTScribe
Project-URL: Repository, https://github.com/dparedesi/YTScribe
Project-URL: Issues, https://github.com/dparedesi/YTScribe/issues
Keywords: youtube,transcript,conference,downloader,archive,subtitles,captions
Classifier: Development Status :: 4 - Beta
Classifier: Environment :: Console
Classifier: Intended Audience :: Developers
Classifier: Intended Audience :: Science/Research
Classifier: License :: OSI Approved :: MIT License
Classifier: Operating System :: OS Independent
Classifier: Programming Language :: Python :: 3
Classifier: Programming Language :: Python :: 3.9
Classifier: Programming Language :: Python :: 3.10
Classifier: Programming Language :: Python :: 3.11
Classifier: Programming Language :: Python :: 3.12
Classifier: Topic :: Multimedia :: Video
Classifier: Topic :: Text Processing
Classifier: Topic :: Utilities
Requires-Python: >=3.9
License-File: LICENSE
Requires-Dist: youtube-transcript-api>=0.6.0
Requires-Dist: pytube>=15.0.0
Requires-Dist: yt-dlp>=2023.0.0
Requires-Dist: tiktoken>=0.5.0
Requires-Dist: pyyaml>=6.0.0
Requires-Dist: requests>=2.31.0
Requires-Dist: platformdirs>=4.0.0
Provides-Extra: dev
Requires-Dist: pytest>=7.0.0; extra == "dev"
Requires-Dist: pytest-cov>=4.0.0; extra == "dev"
Requires-Dist: pytest-mock>=3.10.0; extra == "dev"
Requires-Dist: black>=23.0.0; extra == "dev"
Requires-Dist: ruff>=0.1.0; extra == "dev"
Requires-Dist: mypy>=1.0.0; extra == "dev"
Requires-Dist: pre-commit>=3.0.0; extra == "dev"
Dynamic: license-file
